CHANGES
LICENSE
MANIFEST.in
README.rst
setup.cfg
setup.py
axibot/__init__.py
axibot/action.py
axibot/cmd.py
axibot/colors.py
axibot/config.py
axibot/debug.py
axibot/ebb.py
axibot/job.py
axibot/planning.py
axibot/svg.py
axibot/transform.py
axibot.egg-info/PKG-INFO
axibot.egg-info/SOURCES.txt
axibot.egg-info/dependency_links.txt
axibot.egg-info/entry_points.txt
axibot.egg-info/not-zip-safe
axibot.egg-info/requires.txt
axibot.egg-info/top_level.txt
axibot/server/__init__.py
axibot/server/api.py
axibot/server/handlers.py
axibot/server/plotting.py
axibot/server/state.py
axibot/server/views.py
axibot/tests/__init__.py
axibot/tests/test_cmd.py
axibot/tests/test_debug.py
axibot/tests/test_job.py
axibot/tests/test_planning.py
axibot/tests/test_svg.py
axibot/tests/utils.py
examples/bezier.svg
examples/circles.svg
examples/colors.svg
examples/fonts.svg
examples/line.svg
examples/lines.svg
examples/mixed.svg
examples/polys.svg
examples/rectangles.svg
examples/spiral.svg
examples/usetag.svg
examples/worldmap.svg