Metadata-Version: 2.1
Name: axibot
Version: 0.0.3
Summary: Software for AxiDraw pen plotting robot
Home-page: https://github.com/storborg/axibot
Author: Scott Torborg
Author-email: storborg@gmail.com
License: GPL
Keywords: eibotboard axidraw cam motion pen drawing plotter
Platform: UNKNOWN
Classifier: Development Status :: 3 - Alpha
Classifier: License :: OSI Approved :: GNU General Public License (GPL)
Classifier: Programming Language :: Python :: 3
Classifier: Programming Language :: Python :: 3.5
Classifier: Programming Language :: Python :: 3.6
Classifier: Programming Language :: Python :: 2
Classifier: Programming Language :: Python :: 2.7
Classifier: Environment :: Console
Classifier: Environment :: Web Environment
Classifier: Topic :: Artistic Software
Classifier: Topic :: Multimedia :: Graphics
Classifier: Topic :: Printing
Provides-Extra: server
Provides-Extra: debug
